{
  "Dashboard": {
    "name": null,
    "path": "/admin/",
    "perId": "home"
  },
  "Admins Manage": {
    "Admins": {
      "path": "/admin/alladmins",
      "name": null,
      "perId": "allAdmin"
    },
    "Roles": {
      "path": "/admin/allroles",
      "name": null,
      "perId": "showRoles"
    },
    "Admins Archive": {
      "path": "/admin/adminarchives",
      "name": null,
      "perId": "showRoles"
    }
  },
  "Accounts Manage": {
    "Users": {
      "path": "/admin/allusers",
      "perId": "showUsers"
    },
    "Users Archive": {
      "path": "/admin/userarchives",
      "perId": "showArchivedUser"
    }
  },
  "Products Manage": {
    "Categories": {
      "path": "/admin/allcategories",
      "perId": "showUsers"
    },
    "Brands": {
      "path": "/admin/allbrands",
      "perId": "showArchivedUser"
    },
    "Attribute": {
      "path": "/admin/allattributes",
      "perId": "showArchivedUser"
    },
    "Products": {
      "path": "/admin/allproducts",
      "perId": "showArchivedUser"
    },
    "Products Archive": {
      "path": "/admin/archiveproducts",
      "perId": "showArchivedUser"
    }
  },
  "Orders Manage": {
    "All Order": {
      "path": "/admin/allorder",
      "perId": "showUsers"
    },
    "Tax": {
      "path": "/admin/tax",
      "perId": "showUsers"
    },
    "Delivery": {
      "path": "/admin/delivery",
      "perId": "showUsers"
    }
  },
  "Locations Manage": {
    "Country": {
      "path": "/admin/allcountries",
      "perId": "showUsers"
    }
  },
  "Languages": {
    "name": null,
    "path": "/admin/languages",
    "perId": "showLanguages"
  },
  "Back To Site": {
    "name": null,
    "path": "/",
    "perId": "showLanguages"
  }
}